queue_automator/__init__.py
queue_automator/automator.py
queue_automator/constants.py
queue_automator/maybe.py
queue_automator-0.1.0.dist-info/LICENSE
queue_automator-0.1.0.dist-info/METADATA
queue_automator-0.1.0.dist-info/WHEEL
queue_automator-0.1.0.dist-info/top_level.txt
queue_automator-0.1.0.dist-info/RECORD
