Metadata-Version: 2.1
Name: queue-automator
Version: 0.1.0
Summary: A simple wrapper to build queue multiprocessing pipelines
Home-page: https://github.com/Wason1797/QueueAutomator
Author: Wason1797
Author-email: wabrborich@hotmail.com
Project-URL: Bug Tracker, https://github.com/Wason1797/QueueAutomator/issues
Classifier: Programming Language :: Python :: 3
Classifier: License :: OSI Approved :: MIT License
Classifier: Operating System :: OS Independent
Requires-Python: >=3.6
License-File: LICENSE
